contek_viper/__init__.py
contek_viper/viper_client.py
contek_viper/execution/__init__.py
contek_viper/execution/execution_service_pb2.py
contek_viper/execution/execution_service_pb2_grpc.py
contek_viper/execution/market_signal_pb2.py
contek_viper-3.0.dist-info/METADATA
contek_viper-3.0.dist-info/WHEEL
contek_viper-3.0.dist-info/top_level.txt
contek_viper-3.0.dist-info/zip-safe
contek_viper-3.0.dist-info/RECORD
