Metadata-Version: 2.1
Name: contek-viper
Version: 3.0
Summary: Viper Python Client
Home-page: https://contek.io
Author: contek_bjy
Author-email: bjy@contek.io
License: private
Platform: UNKNOWN
Classifier: Programming Language :: Python :: 3
Classifier: License :: Other/Proprietary License
Classifier: Operating System :: OS Independent
Requires-Python: >=3.6
Requires-Dist: grpcio
Requires-Dist: protobuf
